{
  "typeName": "RPG::System",
  "_": 7829367,
  "actor_collapse_se": {
    "typeName": "RPG::AudioFile",
    "name": "011-System11",
    "pitch": 100,
    "volume": 80
  },
  "battle_bgm": {
    "typeName": "RPG::AudioFile",
    "name": "",
    "pitch": 100,
    "volume": 100
  },
  "battle_end_me": {
    "typeName": "RPG::AudioFile",
    "name": "001-Victory01",
    "pitch": 100,
    "volume": 100
  },
  "battle_start_se": {
    "typeName": "RPG::AudioFile",
    "name": "009-System09",
    "pitch": 100,
    "volume": 80
  },
  "battle_transition": "003-Blind03",
  "battleback_name": "DarkHillsFort",
  "battler_hue": 0,
  "battler_name": "SukiBattler",
  "buzzer_se": {
    "typeName": "RPG::AudioFile",
    "name": "004-System04",
    "pitch": 100,
    "volume": 80
  },
  "cancel_se": {
    "typeName": "RPG::AudioFile",
    "name": "003-System03",
    "pitch": 100,
    "volume": 80
  },
  "cursor_se": {
    "typeName": "RPG::AudioFile",
    "name": "001-System01",
    "pitch": 100,
    "volume": 80
  },
  "decision_se": {
    "typeName": "RPG::AudioFile",
    "name": "002-System02",
    "pitch": 100,
    "volume": 80
  },
  "edit_map_id": 4,
  "elements": [
    "",
    "Fire",
    "Ice",
    "Lightning",
    "Water",
    "Earth",
    "Wind",
    "Light",
    "Darkness",
    "vs Undead",
    "vs Snake",
    "vs Aquatic",
    "vs Beast",
    "vs Goblin",
    "vs Bird",
    "vs Devil",
    "vs Angel",
    "DiD",
    "vs Male",
    "vs Female",
    "vs Armored",
    "SP damage"
  ],
  "enemy_collapse_se": {
    "typeName": "RPG::AudioFile",
    "name": "",
    "pitch": 100,
    "volume": 80
  },
  "equip_se": {
    "typeName": "RPG::AudioFile",
    "name": "005-System05",
    "pitch": 100,
    "volume": 80
  },
  "escape_se": {
    "typeName": "RPG::AudioFile",
    "name": "010-System10",
    "pitch": 100,
    "volume": 80
  },
  "gameover_me": {
    "typeName": "RPG::AudioFile",
    "name": "GameOver",
    "pitch": 100,
    "volume": 100
  },
  "gameover_name": "001-Gameover01",
  "load_se": {
    "typeName": "RPG::AudioFile",
    "name": "008-System08",
    "pitch": 100,
    "volume": 80
  },
  "magic_number": 93727038,
  "party_members": [
    1
  ],
  "save_se": {
    "typeName": "RPG::AudioFile",
    "name": "007-System07",
    "pitch": 100,
    "volume": 80
  },
  "shop_se": {
    "typeName": "RPG::AudioFile",
    "name": "006-System06",
    "pitch": 100,
    "volume": 80
  },
  "start_map_id": 4,
  "start_x": 0,
  "start_y": 0,
  "switches": [
    null,
    "Captive 1",
    "Captive 2",
    "Captive 3",
    "Captive 4",
    "Captive 5",
    "Captive 6",
    "Captive 7",
    "Captive 8",
    "Captive 9",
    "Captive 10",
    "Captive 11",
    "Captive 12",
    "Captive 13",
    "Captive 14",
    "Captive 15",
    "Sister Miyoko Did",
    "Sister Kayuro Did",
    "Sister Miyoko Did2",
    "Sister Kayuro Did2",
    "Captive 1 ()",
    "Captive 2 ()",
    "(Kayuro Did3)",
    "(Alika Did 2)",
    "(Michelle Did 2)",
    "(Alita Did 2)",
    "Captive 1 state 2",
    "Captive 2 state 2",
    "Captive 3 state 2",
    "Captive 4 state 2",
    "Captive 5 state 2",
    "Captive 6 state 2",
    "Captive 7 state 2",
    "Captive 8 state 2",
    "Captive 9 state 2",
    "Captive 10 state 2",
    "FirstInspection(Desert)",
    "",
    "Trap",
    "",
    "",
    "",
    "",
    "",
    "",
    "Suki poisoned",
    "",
    "",
    "",
    "",
    "",
    "Escape sequence",
    "Game over",
    "UsedMobRush",
    "Carriage Travel",
    "MinigameUnderProgress",
    "GenieBlock",
    "SidedWithNatives",
    "BanditCapture",
    "MegumiRescue",
    "Bandit capture monologue prevention",
    "",
    "",
    "",
    "",
    "",
    "",
    "",
    "",
    "",
    "",
    "",
    "",
    "",
    "DoneAmazonMission",
    "DoneVamireMission",
    "Forest archer is caught",
    "Forest watermage is caught",
    "Forest firemage is caught",
    "Forest Dryad is caught",
    "Forest Foxgirl is caught",
    "Forest Catgirl is caught",
    "GWhiteWomanIsCaught",
    "GGreenWomanCaught",
    "GRedWomanCaught",
    "GBlondeWomanCaught",
    "ArcheologistBlueCaught",
    "ArcheologistRedCaught",
    "ArcheologistBlondeCaught",
    "BikinigirlRedCaught",
    "BikinigirlBlondeCaught",
    "BikinigirlBrunetteCaught",
    "",
    "",
    "Main Objest (desert)",
    "",
    "Test Switch (Schm)",
    "",
    "",
    "",
    "",
    "Rescue help shown",
    "Ambush help shown",
    "",
    "",
    "",
    "",
    "",
    "",
    "",
    "",
    "",
    "",
    "",
    "",
    "",
    "",
    "",
    "",
    "",
    "",
    "",
    "",
    "",
    "Private Cell dialogue disabled",
    "Tutorial text switch",
    "Prologue",
    "AllyEscapePractice",
    "Epilogue",
    "Carol the ally",
    "Carol the captive",
    "Done Wedding mission",
    "Invisibility pot in use",
    "Done third quest",
    "Good path",
    "Bad path",
    "Quest switch 1",
    "Quest switch 2",
    "Done fourth quest",
    "Call Easy",
    "Call Normal",
    "Call Hard",
    "Call Impossible",
    "Impossible",
    "Player is ungagged",
    "Ambush",
    "Player is blindfolded",
    "Leroy is Weak",
    "InvisibilityCancel",
    "Athena is rescued",
    "Damsel Cheat",
    "Haggle captive 1",
    "Haggle captive 2",
    "Haggle captive 3",
    "Haggle captive 4",
    "Haggle captive 5",
    "Haggle captive 6",
    "Haggle captive 7",
    "Haggle captive 8",
    "Haggle captive 9",
    "Haggle captive 10",
    "Haggle captive 11",
    "Haggle captive 12",
    "Haggle captive 13",
    "Haggle captive 14",
    "Haggle captive 15",
    "Haggle captive 16",
    "Haggle captive 17",
    "Haggle captive 18",
    "Haggle captive 19",
    "",
    "",
    "",
    "",
    "",
    "",
    "",
    "",
    "",
    "",
    "",
    "",
    "",
    "",
    "",
    "",
    "",
    "",
    "",
    "",
    "",
    "",
    "",
    "",
    "",
    "",
    "",
    "",
    "",
    "",
    "",
    "Kept captive 1",
    "Kept captive 2",
    "Kept captive 3",
    "Kept captive 4",
    "Kept captive 5",
    "Kept captive 6",
    "Kept captive 7",
    "Kept captive 8",
    "Kept captive 9",
    "Kept captive 10",
    "Kept captive 11",
    "Kept captive 12",
    "Kept captive 13",
    "Kept captive 14",
    "Kept captive 15",
    "Kept captive 16",
    "Kept captive 17",
    "Kept captive 18",
    "Kept captive 19",
    "",
    "",
    "",
    "",
    "",
    "",
    "",
    "",
    "",
    "",
    "",
    "",
    "",
    "",
    "",
    "",
    "",
    "",
    "",
    "",
    "",
    "",
    "",
    "",
    "",
    "",
    "",
    "",
    "",
    "",
    "",
    "Mission 1 rep A",
    "Mission 1 rep B",
    "Mission 2 rep A",
    "Mission 2 rep B",
    "Mission 3 rep A",
    "Mission 3 rep B",
    "Mission 4 rep A",
    "Mission 4 rep B",
    "Mission 5 rep A",
    "Mission 5 rep B",
    "Mission 6 rep A",
    "Mission 6 rep B",
    "Mission 7 rep A",
    "Mission 7 rep B",
    "Mission 8 rep A",
    "Mission 8 rep B",
    "Mission 9 rep A",
    "Mission 9 rep B",
    "Mission 10 rep A",
    "Mission 10 rep B",
    "",
    "",
    "",
    "",
    "",
    "PC is occupied",
    "",
    "Lady's Maid in PC",
    "",
    "",
    "Marcia in PC",
    "",
    "",
    "",
    "",
    "",
    "",
    "",
    "",
    "",
    "",
    "",
    "",
    "",
    "",
    "",
    "",
    "",
    "",
    "",
    "Enemy 1 is tied up",
    "Enemy 2 is tied up",
    "Enemy 3 is tied up",
    "Enemy 4 is tied up",
    "Enemy 5 is tied up",
    "Enemy 6 is tied up",
    "Enemy 7 is tied up",
    "Enemy 8 is tied up",
    "Suki is tied up",
    "Daytime switch",
    "Nighttime switch",
    "Suki Tyable",
    "Carol Tyable",
    "1OrMoreActorTyable",
    "Escaped battle",
    "Lost the battle",
    "Won the battle",
    "Carol is tied up",
    "Battle Dialogue",
    "Prevent BGM change",
    "Healed (battle)",
    "SukiHealed/Damaged check",
    "CarolHealed/Damaged check",
    "LeroyHealed/Damaged check",
    "KuruiHealed/Damaged check",
    "Watcher",
    "Alert",
    "Evasion",
    "Caution",
    "Music watcher",
    "StealthItemEnabeled",
    "SGrenade in use",
    "Alert Timer Prevention",
    "GuardMovementPrevention",
    "Time-of-day switch",
    "Alert Update",
    "Transport switch",
    "Terrain tag switch",
    "Faceset Scene",
    "Music switch",
    "Minigame switch",
    "Visit",
    "ESCAPE: No guard",
    "reserved",
    "reserved",
    "Music switch II",
    "SKIP cheat",
    "Easy",
    "Normal",
    "Hard",
    "Jonas Inspection",
    "Jonas Defeated",
    "Ann Inspection",
    "Maria Inspection",
    "Linda Inspection",
    "Cilie Inspection",
    "Tom Defeated",
    "Tom Inspection",
    "Peter Inspection",
    "Sophie Inspection",
    "Olga Inspection",
    "Sara Inspection",
    "George Inspection",
    "George Defeated",
    "Peter Defeated",
    "Bob Inspection",
    "Bob Defeated",
    "Herbert Inspection",
    "Fred Inspection",
    "Fred Defeated",
    "Herbert Defeated",
    "Evan Inspection",
    "Evan Defeated",
    "Steven Inspection",
    "Steven Defeated",
    "Kurui Tyable",
    "Kurui is tied up",
    "Genie is tied up",
    "Leroy is KO'd",
    "Player is hidden",
    "Carol in the party",
    "Athena Tyable",
    "Athena is tied up",
    "Athena in the party",
    "AthenaHealed/Damage check",
    "Genie Locked",
    "Suki Locked",
    "Evelyn Tyable",
    "Evelyn is tied up",
    "Evelyn in the party",
    "EvelynHealed/Damage check",
    "MoreThan1ActorTyable",
    "IgnoreStates(battle)",
    "DisableSubdueError(Battle)",
    "",
    "",
    "",
    "",
    "",
    "",
    "Notoriety wait",
    "Notoriety timer",
    "Notoriety graphic is shown",
    "Hide cancel",
    "Fade",
    "Disable Tears",
    "Tremble switch (vertical screen shake)",
    "FlorianMap",
    "Viewing World Map",
    "",
    "",
    "",
    "",
    "",
    "",
    "",
    "",
    "",
    "",
    "",
    "",
    "Sven Inspection",
    "Sven Defeated",
    "Kim Inspection",
    "Kim Defeated",
    "Jonas is within radius",
    "Tom is within radius",
    "Peter is within radius",
    "George is within radius",
    "Bob is within radius",
    "Fred is within radius",
    "Herbert is within radius",
    "Evan is within radius",
    "Steven is within radius",
    "Kim is within radius",
    "Sven is within radius",
    "reserved",
    "reserved",
    "reserved",
    "reserved",
    "",
    "",
    "",
    "",
    "",
    "",
    "",
    "",
    "",
    "",
    "Jonas disabled",
    "Tom disabled",
    "Peter disabled",
    "George disabled",
    "Bob disabled",
    "Fred disabled",
    "Herbert disabled",
    "Evan disabled",
    "Steven disabled",
    "Kim disabled",
    "Sven disabled",
    "reserved",
    "reserved",
    "reserved",
    "reserved",
    "",
    "",
    "",
    "",
    "",
    "Alert",
    "Pole 1 Occ",
    "Pole 2 Occ",
    "Pole 3 Occ",
    "",
    "Mission 1 Bonus",
    "Mission 2 Bonus",
    "Mission 3 Bonus",
    "Mission 4 Bonus",
    "Mission 5 Bonus",
    "Mission 6 Bonus",
    "Mission 7 Bonus",
    "Mission 8 Bonus",
    "Mission 9 Bonus",
    "Mission 10 Bonus",
    "",
    "",
    "",
    "",
    "",
    "",
    "",
    "",
    "",
    "",
    "",
    "",
    "",
    "",
    "",
    "Day switch",
    "Night switch",
    "Good weather",
    "Bad weather",
    "",
    "",
    "",
    "",
    "",
    "",
    "",
    "",
    "",
    "",
    "",
    "",
    "",
    "",
    "",
    "",
    "",
    "",
    "",
    "",
    "",
    "Shown help image 1",
    "Shown help image 2",
    "Shown help image 3",
    "Shown help image 4",
    "Shown help image 5",
    "Shown help image 6",
    "Shown help image 7",
    "Shown help image 8",
    "Shown help image 9",
    "Shown help image 10",
    "Shown help image 11",
    "Shown help image 12",
    "Shown help image 13",
    "Shown help image 14",
    "Shown help image 15",
    "",
    "",
    "",
    "",
    "",
    "",
    "",
    "",
    "",
    "",
    "Item Menu",
    "Mob Rush unlocked",
    "Damsel Ambush Down",
    "Damsel Ambush Cancel",
    "Battle Subdue Sequence",
    "Custom Fade Exception",
    "Battle Fade",
    "Surrender Cheat",
    "Mature Cheat",
    "SukiNoEquip",
    "Custom Text Window position",
    "Classy Cheat",
    "OneLiner Cheat",
    "Christmas",
    "",
    "",
    "",
    "",
    "",
    "",
    "",
    "",
    "",
    "",
    "",
    "Achieve: Initiation",
    "Achieve: Negotiate with Hostages",
    "Achieve: Partner in Crime",
    "BobBlindspot",
    "JonasBlindspot",
    "FredBlindspot",
    "GeorgeBlindspot",
    "MGDealerTurn",
    "",
    "",
    "",
    "",
    "",
    "",
    "",
    "",
    "",
    "",
    "",
    "",
    "",
    "",
    "",
    "",
    ""
  ],
  "test_battlers": [
    {
      "typeName": "RPG::System::TestBattler",
      "actor_id": 1,
      "armor1_id": 0,
      "armor2_id": 9,
      "armor3_id": 106,
      "armor4_id": 0,
      "level": 15,
      "weapon_id": 39
    },
    {
      "typeName": "RPG::System::TestBattler",
      "actor_id": 2,
      "armor1_id": 0,
      "armor2_id": 0,
      "armor3_id": 40,
      "armor4_id": 27,
      "level": 15,
      "weapon_id": 13
    }
  ],
  "test_troop_id": 98,
  "title_bgm": {
    "typeName": "RPG::AudioFile",
    "name": "Scirocco (Theme for DIDnapper) by napdog",
    "pitch": 100,
    "volume": 100
  },
  "title_name": "v17title",
  "variables": [
    null,
    "Moving Adjusted X",
    "Moving Adjusted Y",
    "Captives (mission)",
    "Player X",
    "Player Y",
    "Girls in cellar",
    "Current moveable captives",
    "Captives (all)",
    "Map ID",
    "Lives/TimesCaught",
    "Quests done",
    "Quest variable",
    "Chloroform variable",
    "Rope amount",
    "Cheat variable",
    "StoryProgress",
    "Captures needed (battle)",
    "Captures (battle)",
    "Guards needed defeated (battle)",
    "Guards defeated (battle)",
    "TimesCaughtRecorder",
    "Minigame Progress",
    "Mission stage",
    "Random #",
    "Time Points",
    "DI easily afraid",
    "DI easily happy",
    "DI easily angry",
    "DI easily shy",
    "DI easily sad",
    "DI Anger",
    "DI Shyness",
    "DI Sadness",
    "DI Fear",
    "DI Happiness",
    "DI Surprise",
    "DI Tickle Tears",
    "DI Ticklish",
    "DI Masochist",
    "DI Homophilia",
    "DI Arousal",
    "DI Arousal Max Limit",
    "DI Arousal Min Limit",
    "DI Disposition",
    "MGDrawCard",
    "MGCheckAce",
    "MGDealerTotal",
    "MGPlayerTotal",
    "MGDealerPhase",
    "MGPlayerPhase",
    "Mission 1 highscore",
    "Mission 2 highscore",
    "Mission 3 highscore",
    "Mission 4 highscore",
    "Mission 5 highscore",
    "Mission 6 highscore",
    "Mission 7 highscore",
    "Mission 8 highscore",
    "Mission 9 highscore",
    "Mission 10 highscore",
    "",
    "",
    "",
    "",
    "",
    "",
    "",
    "",
    "",
    "",
    "",
    "",
    "",
    "",
    "",
    "Menu Max #",
    "Menu Cursor #",
    "Panel Menu #",
    "Sp. damsel Gag #",
    "Sp. damsel Blindfold#",
    "Sp. damsel Mood #",
    "Sp. damsel Outf. #",
    "Sp. damsel Bind. #",
    "Outfits Max",
    "BlinkingCounter",
    "MaxPartySize",
    "BlockActorID",
    "CZ captives",
    "CZ Max cap",
    "CZ new captive ID",
    "Timer(PetInParty)",
    "ShyEyesStage",
    "EyesClosed",
    "Menu Cursor 2 #",
    "Sp. damsel Pos. #",
    "Escape perk",
    "Guard fail count",
    "Gag meter",
    "Legs meter",
    "Arms meter",
    "Personality: Overall Goodness",
    "Personality: Curiosity",
    "Personality: Tidyness",
    "Personality: Socialness",
    "Personality: Empathy/goodness",
    "Personality: Stressed/Moody",
    "PersonalityMidline",
    "",
    "",
    "",
    "",
    "Event spawn 14",
    "Event spawn 13",
    "Event spawn 12",
    "Event spawn 11",
    "Event spawn 10",
    "Event spawn 9",
    "Event Spawn 8",
    "Event Spawn 7",
    "Event Spawn 6",
    "Event Spawn 5",
    "EventSpawn4",
    "EventSpawn3",
    "EventSpawn2",
    "EventSpawn1",
    "Record Max HP",
    "Record Max SP",
    "Damsel Ambush Max Attempts",
    "Damsel Ambush Hits",
    "Damsel Ambush Attemtps",
    "Damsel Ambush progress",
    "Mission sidequest stage",
    "Lost money",
    "IKO count",
    "Mission money price",
    "Suki level recorder(DamselX)",
    "Suki new level (DamselY)",
    "Carol level recorder(DamselDifX)",
    "Carol new level(DamselDifY)",
    "Leroy level recorder",
    "Leroy new level",
    "Mission rank",
    "Battle win EXP",
    "Kurui level recorder",
    "AdditionalSecurePoints",
    "Genie Captures",
    "Rope difference",
    "Temporary recorder",
    "Evasion timer",
    "New EXP",
    "Actors captured (battle)",
    "ActorsInParty(Normal)",
    "",
    "Current HP/percentage",
    "Males needed defeated (battle)",
    "Males defeated (battle)",
    "Troop ID",
    "Battle variable",
    "Momentarily random variable",
    "Game difficulty",
    "Time played (general)",
    "Mission time",
    "Mission time minutes",
    "Mission time seconds",
    "Mission time factor",
    "Mission points",
    "Times detected",
    "Stealth items used",
    "Battles won",
    "Player hiding place",
    "Genie wishes",
    "Total mission points",
    "Mission target",
    "Mission variable 2",
    "Mission ID in progress",
    "PirateCaptainDefeated",
    "(5th mission preparations)",
    "General Party#",
    "Suki Party#",
    "Carol Party#",
    "Leroy Party#",
    "Kurui Party#",
    "Genie Party #",
    "Athena Party #",
    "Evelyn Party #",
    "reserved",
    "reserved",
    "reserved",
    "Notoriety Evasion wait (remove)",
    "Notoriety",
    "Suspicion (what is this?)",
    "Alert",
    "Notoriety Bonus (remove)",
    "Notoriety graphic stage (what?)",
    "Notoriety respawn wait (remove)",
    "Battle type",
    "Recovery %",
    "Mob distance",
    "Guards to add",
    "Enemies within radius",
    "LineOfSight",
    "Reinforcements",
    "Route Entry",
    "Terrain Tag",
    "Normal Vision",
    "Inspection Vision",
    "Evasion Vision",
    "Caution Vision",
    "Coming player X",
    "Coming player Y",
    "Coming Map ID",
    "Music variable",
    "Grenade counter",
    "Times slept",
    "Mission 1 repeated",
    "Mission 2 repeated",
    "Mission 3 repeated",
    "Mission 4 repeated",
    "Mission 5 repeated",
    "Mission 6 repeated",
    "Mission 7 repeated",
    "Mission 8 repeated",
    "Mission 9 repeated",
    "Mission 10 repeated",
    "",
    "Jonas X",
    "Jonas Y",
    "Jonas DifX",
    "Jonas DifY",
    "George X",
    "George Y",
    "George DifX",
    "George DifY",
    "Bob X",
    "Bob Y",
    "Bob DifX",
    "Bob DifY",
    "Fred X",
    "Fred Y",
    "Fred DifX",
    "Fred DifY",
    "Tom X",
    "Tom Y",
    "Tom DifX",
    "Tom DifY",
    "Peter X",
    "Peter Y",
    "Peter DifX",
    "Peter DifY",
    "",
    "Herbert X",
    "Herbert Y",
    "Herbert DifX",
    "Herbert DifY",
    "Evan X",
    "Evan Y",
    "Evan DifX",
    "Evan DifY",
    "Steven X",
    "Steven Y",
    "Steven DifX",
    "Steven DifY",
    "Kim X",
    "Kim Y",
    "Kim DifX",
    "Kim DifY",
    "Sven X",
    "Sven Y",
    "Sven DifX",
    "Sven DifY",
    "",
    "",
    "",
    "",
    "",
    "Captive 1 hidden",
    "Captive 2 hidden",
    "Captive 3 hidden",
    "Captive 4 hidden",
    "Captive 5 hidden",
    "Captive 6 hidden",
    "Captive 7 hidden",
    "Captive 8 hidden",
    "Captive 9 hidden",
    "Captive 10 hidden",
    "Captive 11 hidden",
    "reserved",
    "reserved",
    "reserved",
    "reserved",
    "reserved",
    "reserved",
    "reserved",
    "reserved",
    "reserved",
    "reserved",
    "reserved",
    "reserved",
    "reserved",
    "reserved",
    "Ann X",
    "Ann Y",
    "Ann DifX",
    "Ann DifY",
    "Maria X",
    "Maria Y",
    "Maria DifX",
    "Maria DifY",
    "Linda X",
    "Linda Y",
    "Linda DifX",
    "Linda DifY",
    "Cilie X",
    "Cilie Y",
    "Cilie DifX",
    "Cilie DifY",
    "Sophie X",
    "Sophie Y",
    "Sophie DifX",
    "Sophie DifY",
    "Olga X",
    "Olga Y",
    "Olga DifX",
    "Olga DifY",
    "",
    "Sara X",
    "Sara Y",
    "Sara DifX",
    "Sara DifY",
    "Event Screen X",
    "Event Screen Y",
    "Pre-Menu X",
    "Pre-Menu Y",
    "Pre-Menu Map ID",
    "PreviousMap X",
    "PreviousMap Y",
    "PreviousMap ID",
    "CMM progress",
    "Terrain Tag Update",
    "TempMapReset#",
    "EscapeEXP",
    "MinigameMisses",
    "EscapeLevel",
    "Instant recorder",
    "Minigame variable",
    "ButtonID",
    "Jukebox",
    "Fortune",
    "Field ID",
    "GagVariable",
    "Jonas Distance",
    "Tom Distance",
    "Peter Distance",
    "George Distance",
    "Bob Distance",
    "Fred Distance",
    "Herbert Distance",
    "Evan Distance",
    "Steven Distance",
    "Kim Distance",
    "Sven Distance",
    "",
    "",
    "",
    "",
    "",
    "",
    "",
    "",
    "",
    "",
    "",
    "",
    "",
    "",
    "Available actors (battle)",
    "Enemies (battle)",
    "Mob Rush countdown",
    "Tyable Actors",
    "",
    "Map changed",
    "EXP counter",
    "Current rope amount",
    "Carol DI stage",
    "Athena DI stage",
    "GameVersion",
    "OldGameVersion",
    "Shopkeeper stage",
    "MissionRepCutscene",
    "ActorsOnStandby",
    "Megumi stage",
    "Casino event stage",
    "QueenKamalaStage",
    "Burglar sidequest stage",
    "ActorsCaptured(map)",
    "ActorsInPrison",
    "Archeologist stage",
    "Cilia stage",
    "Evelyn stage",
    "Esther stage",
    "Year(XXXX)",
    "Month(01-12)",
    "Day(01-31)",
    "Hour(XX)",
    "Minute(XX)",
    "Second(XX)",
    "Window Position X",
    "Window Position Y",
    "Previous direction",
    "XRecorderForWorldMap",
    "YRecorderForWorldMap",
    "",
    "",
    "",
    "",
    "",
    "",
    "",
    "",
    "",
    "",
    "",
    "",
    "",
    "DI menu freeze variable",
    "Guards type 1",
    "Guards type 2",
    "Guards type 3",
    "Guards type 4",
    "Guards type 5",
    "Guards type 6",
    "Guards type 7",
    "Guards type 8",
    "Guards type 9",
    "Guards type 10",
    "",
    "",
    "",
    "",
    "",
    "",
    "",
    "",
    "",
    "",
    "",
    "",
    "",
    "",
    "",
    "Help picture lookthrough",
    "Max image number",
    "Mission display #",
    "Special Items in inventory",
    "Item image #",
    "Item Minimum #",
    "Item Maximum #",
    "MenuResultID",
    "BG X",
    "BG Y",
    "Additional X",
    "Additional Y",
    "Active X",
    "Active Y",
    "Adjusted X",
    "Adjusted Y",
    "Animation 1",
    "Animation 2",
    "Animation 3",
    "Animation 4",
    "Animation 5",
    "Arms struggle",
    "Legs struggle",
    "Gag struggle",
    "Minigame/menu item ID",
    "Invisibility Potion counter",
    "UniqueEscapeScenes",
    "Digit Calculation",
    "Digit 1",
    "Digit 2",
    "Digit 1 X",
    "Digit 1 Y",
    "Digit 2 X",
    "Digit 2 Y",
    "BGM ID",
    "Constant 0",
    "Minigame speed",
    "DA Hitbox minimum",
    "DA Hitbox maximum",
    "Mermaid stage",
    "Angel stage",
    "Assassin stage",
    "Enemy 1 secure level",
    "Enemy 2 secure level",
    "Enemy 3 secure level",
    "Enemy 4 secure level",
    "Enemy 5 secure level",
    "Enemy 6 secure level",
    "Enemy 7 secure level",
    "Enemy 8 secure level",
    "DI Female Guard Mood",
    "DI Female Guard Gag",
    "DI Female Guard Blindfold",
    "DI Lady's Maid Gag",
    "DI Lady's Maid Blindfold",
    "DI Lady's Maid Mood",
    "DI Mermaid Gag",
    "DI Mermaid Blindfold",
    "DI Mermaid Mood",
    "DI Angel Gag",
    "DI Angel Blindfold",
    "DI Angel Mood",
    "DI Marcia Gag",
    "DI Marcia Blindfold",
    "DI Marcia Mood",
    "DI Carol Gag",
    "DI Carol Blindfold",
    "DI Carol Mood",
    "DI Athena Gag",
    "DI Athena Blindfold",
    "DI Athena Mood",
    "DI Shopkeeper Gag",
    "DI Shopkeeper Blindfold",
    "DI Shopkeeper Mood",
    "",
    "Wall X (temp)",
    "Wall Y (temp)",
    "Wall X Dif (temp)",
    "Wall Dif Y (temp)",
    "Wall 2 X (temp)",
    "Wall 2 Y (temp)",
    "TreeFence X",
    "TreeFence Y",
    "Wall X Left",
    "Wall X Right",
    "Wall Y Up",
    "Wall Y Down",
    "",
    "",
    "",
    "",
    "",
    "",
    "",
    "",
    "",
    "",
    "",
    "",
    "",
    "Suki party state",
    "Carol party state",
    "Leroy party state",
    "Eve party state",
    "Evelyn party state",
    "Athena party state",
    "Genie party state",
    "",
    "",
    "Suki Secure level",
    "Carol Secure level",
    "Eve Secure level",
    "Athena Secure level",
    "Evelyn Secure level",
    "",
    "",
    "",
    "",
    "",
    "",
    "",
    "",
    "",
    "",
    "",
    "DI Amazon Mood",
    "DI Amazon Gag",
    "DI Amazon Blindfold",
    "DI Archeologist Mood",
    "DI Archeologist Gag",
    "DI Archeologist Blindfold",
    "DI Cilia Mood",
    "DI Cilia Gag",
    "DI Cilia Blindfold",
    "DI Evelyn Mood",
    "DI Evelyn Gag",
    "DI Evelyn Blindfold",
    "DI Burglar Mood",
    "DI Burglar Gag",
    "DI Burglar Blindfold",
    "",
    "",
    "",
    "",
    "",
    "",
    "",
    "",
    "",
    "",
    "CZ Captive 1",
    "CZ Captive 2",
    "CZ Captive 3",
    "CZ Captive 4",
    "CZ Captive 5",
    "CZ Captive 6",
    "CZ Captive 7",
    "CZ Captive 8",
    "CZ Captive 9",
    "CZ Captive 10",
    "CZ Captive 11",
    "CZ Captive 12",
    "CZ Captive 13",
    "CZ Captive 14",
    "CZ Captive 15",
    "",
    "",
    "",
    "",
    "",
    "",
    "",
    "",
    "",
    "",
    "Lady's Maid stage",
    "Menu button delay",
    "PCGagsMax",
    "Wedding quest stage",
    "Temp. quest stage",
    "Alyssa stage",
    "Burglar PC stage",
    "Quest variable 2",
    "Quest variable 3",
    "Quest variable 4",
    "Quest variable 5",
    "CameoQuestStage",
    "SukiTickleCounter",
    "Succubus stage",
    "SlaverQuestStage",
    "",
    "",
    "",
    "",
    "",
    "",
    "",
    "",
    "",
    "",
    "PC storage (Suki Disposition)",
    "Carol Disposition",
    "Athena Disposition",
    "Evelyn Disposition",
    "Female Guard Disposition",
    "Maid Disposition",
    "Marica Disposition",
    "Angel Disposition",
    "Mermaid Disposition",
    "Shopkeeper Disposition",
    "Archaeologist Disposition",
    "Queen Hektala Disposition",
    "Cilia Disposition",
    "Burglar Disposition",
    "Alyssa Disposition",
    "Disposition",
    "Disposition",
    "Disposition",
    "Disposition",
    "Disposition",
    "",
    "",
    "",
    "",
    "",
    "",
    "",
    "",
    "",
    "",
    "",
    "",
    "",
    "",
    "",
    "",
    "",
    "",
    "",
    "",
    "",
    "",
    "",
    "",
    "",
    "",
    "",
    "",
    "",
    ""
  ],
  "windowskin_name": "001-Blue01dark2",
  "words": {
    "typeName": "RPG::System::Words",
    "agi": "AGI",
    "armor1": "Off-Hand",
    "armor2": "Head",
    "armor3": "Body",
    "armor4": "Accessory",
    "atk": "ATK",
    "attack": "Attack",
    "dex": "DEX",
    "equip": "Equip",
    "gold": "Gold",
    "guard": "Defend",
    "hp": "HP",
    "int": "INT",
    "item": "Item",
    "mdef": "MDEF",
    "pdef": "PDEF",
    "skill": "Skill",
    "sp": "SP",
    "str": "STR",
    "weapon": "Weapon"
  }
}